macrometa_target_postgres/__init__.py
macrometa_target_postgres/db_sync.py
macrometa_target_postgres-1.0.0.dist-info/entry_points.txt
macrometa_target_postgres-1.0.0.dist-info/LICENSE
macrometa_target_postgres-1.0.0.dist-info/WHEEL
macrometa_target_postgres-1.0.0.dist-info/METADATA
macrometa_target_postgres-1.0.0.dist-info/RECORD
