Metadata-Version: 2.1
Name: macrometa-target-postgres
Version: 1.0.0
Summary: Pipelinewise target for writing data into Postgres.
License: Apache-2.0
Keywords: ELT,Connectors,Workflows,Macrometa,Target,Postgres
Author: Macrometa
Author-email: info@macrometa.com
Requires-Python: >=3.8.1,<3.11
Classifier: License :: OSI Approved :: Apache Software License
Classifier: Operating System :: OS Independent
Classifier: Programming Language :: Python :: 3
Classifier: Programming Language :: Python :: 3.9
Classifier: Programming Language :: Python :: 3.10
Classifier: Programming Language :: Python :: 3
Classifier: Programming Language :: Python :: 3.9
Requires-Dist: c8connector (>=0.0.29)
Requires-Dist: inflection (==0.3.1)
Requires-Dist: joblib (==1.2.0)
Requires-Dist: pipelinewise-singer-python (==1.2.0)
Requires-Dist: prometheus-client (==0.16.0)
Requires-Dist: psycopg2-binary (==2.9.3)
Requires-Dist: pylint (==2.6.0)
Requires-Dist: pytest (==6.2.5)
Requires-Dist: pytest-cov (==2.10.1)
Project-URL: Bug Tracker, https://github.com/Macrometacorp/macrometa-target-postgres/issues
Project-URL: Homepage, https://www.macrometa.com/
